agniapi/__init__.py
agniapi/app.py
agniapi/blueprints.py
agniapi/cache.py
agniapi/cli.py
agniapi/config.py
agniapi/content_negotiation.py
agniapi/database.py
agniapi/dependencies.py
agniapi/exceptions.py
agniapi/forms.py
agniapi/limiter.py
agniapi/middleware.py
agniapi/monitoring.py
agniapi/openapi.py
agniapi/py.typed
agniapi/request.py
agniapi/response.py
agniapi/routing.py
agniapi/security.py
agniapi/sessions.py
agniapi/static.py
agniapi/streaming.py
agniapi/templating.py
agniapi/testing.py
agniapi/types.py
agniapi/websockets.py
agniapi/mcp/__init__.py
agniapi/mcp/client.py
agniapi/mcp/server.py
agniapi/mcp/tools.py
agniapi/mcp/types.py
agniapi-0.1.1.dist-info/licenses/LICENSE
agniapi-0.1.1.dist-info/METADATA
agniapi-0.1.1.dist-info/WHEEL
agniapi-0.1.1.dist-info/entry_points.txt
agniapi-0.1.1.dist-info/top_level.txt
agniapi-0.1.1.dist-info/RECORD
