Metadata-Version: 2.4
Name: agniapi
Version: 0.1.1
Summary: A unified REST API framework combining Flask and FastAPI features with built-in MCP support
Author-email: AIMLDev726 <aistudentlearn4@gmail.com>
Maintainer-email: AIMLDev726 <aistudentlearn4@gmail.com>
License: MIT
Project-URL: Homepage, https://github.com/AIMLDev726/agniapi
Project-URL: Documentation, https://github.com/AIMLDev726/agniapi/blob/main/README.md
Project-URL: Repository, https://github.com/AIMLDev726/agniapi
Project-URL: Bug Tracker, https://github.com/AIMLDev726/agniapi/issues
Keywords: api,rest,web,framework,async,flask,fastapi,mcp,model-context-protocol
Classifier: Development Status :: 4 - Beta
Classifier: Intended Audience :: Developers
Classifier: License :: OSI Approved :: MIT License
Classifier: Operating System :: OS Independent
Classifier: Programming Language :: Python :: 3
Classifier: Programming Language :: Python :: 3.9
Classifier: Programming Language :: Python :: 3.10
Classifier: Programming Language :: Python :: 3.11
Classifier: Programming Language :: Python :: 3.12
Classifier: Programming Language :: Python :: 3.13
Classifier: Topic :: Internet :: WWW/HTTP :: HTTP Servers
Classifier: Topic :: Internet :: WWW/HTTP :: WSGI :: Application
Classifier: Topic :: Software Development :: Libraries :: Application Frameworks
Classifier: Topic :: Software Development :: Libraries :: Python Modules
Classifier: Framework :: AsyncIO
Requires-Python: >=3.9
License-File: LICENSE
Requires-Dist: starlette>=0.27.0
Requires-Dist: werkzeug>=2.3.0
Requires-Dist: pydantic>=2.0.0
Requires-Dist: click>=8.0.0
Requires-Dist: httpx>=0.24.0
Requires-Dist: typing-extensions>=4.0.0
Requires-Dist: uvicorn[standard]>=0.18.0
Requires-Dist: mcp>=1.0.0
Requires-Dist: PyJWT>=2.0.0
Requires-Dist: jinja2>=3.0.0
Requires-Dist: python-multipart>=0.0.5
Requires-Dist: email-validator>=1.1.0
Provides-Extra: dev
Requires-Dist: pytest>=7.0.0; extra == "dev"
Requires-Dist: pytest-asyncio>=0.21.0; extra == "dev"
Requires-Dist: pytest-cov>=4.0.0; extra == "dev"
Requires-Dist: black>=23.0.0; extra == "dev"
Requires-Dist: isort>=5.0.0; extra == "dev"
Requires-Dist: flake8>=6.0.0; extra == "dev"
Requires-Dist: mypy>=1.0.0; extra == "dev"
Requires-Dist: pre-commit>=3.0.0; extra == "dev"
Provides-Extra: docs
Requires-Dist: mkdocs>=1.4.0; extra == "docs"
Requires-Dist: mkdocs-material>=9.0.0; extra == "docs"
Requires-Dist: mkdocstrings[python]>=0.20.0; extra == "docs"
Provides-Extra: production
Requires-Dist: gunicorn>=20.0.0; extra == "production"
Provides-Extra: all
Requires-Dist: agniapi[dev,docs,production]; extra == "all"
Dynamic: license-file
